{"capturedAt":"2026-07-23T00:13:09Z","repository":"Onmaynec/Nexora","tag":"v3.3.0","tagSha":"a46c080e12b9081b448dad6426bf7c44156114cd","workflowRuns":[{"conclusion":"failure","created_at":"2026-07-22T23:58:34Z","event":"workflow_run","head_branch":"main","head_sha":"a46c080e12b9081b448dad6426bf7c44156114cd","html_url":"https://github.com/Onmaynec/Nexora/actions/runs/29967729776","id":29967729776,"name":"Nexora 3 release","run_number":411,"status":"completed","updated_at":"2026-07-23T00:02:01Z"},{"conclusion":"success","created_at":"2026-07-22T23:56:37Z","event":"push","head_branch":"main","head_sha":"a46c080e12b9081b448dad6426bf7c44156114cd","html_url":"https://github.com/Onmaynec/Nexora/actions/runs/29967637097","id":29967637097,"name":"Project website","run_number":71,"status":"completed","updated_at":"2026-07-22T23:57:11Z"},{"conclusion":"success","created_at":"2026-07-22T23:56:37Z","event":"push","head_branch":"main","head_sha":"a46c080e12b9081b448dad6426bf7c44156114cd","html_url":"https://github.com/Onmaynec/Nexora/actions/runs/29967637087","id":29967637087,"name":"CI","run_number":447,"status":"completed","updated_at":"2026-07-22T23:58:32Z"}]}
